{
  "action": "UpdateDataClassifier",
  "actionparameters": {
    "input": {
      "id": "BUILTIN-test",
      "patch": {
        "severity": "HIGH"
      }
    },
    "selection": [
      {
        "dataClassifier": [
          "id",
          "name",
          "description"
        ]
      }
    ]
  },
  "id": "12345-3f00-41d8-a0d6-12345",
  "log_type": "auditLogEntries",
  "requestid": "12345-1d9b-49e8-a3e2-12345",
  "serviceaccount": null,
  "sourceip": "8.8.8.8",
  "status": "FAILED",
  "timestamp": "2024-05-26 03:40:36.761",
  "user": {
    "id": "test@wiz.io",
    "name": "test@wiz.io"
  },
  "useragent": "Mozilla/5.0 (X11; Linux x86_64) AppleWebKit/537.36 (KHTML, like Gecko) Chrome/124.0.0.0 Safari/537.36"
}
